{"personal-data":{"first-name":["name"],"last-name":["surname"],"phone":["123456789"],"country":["Afghanistan"],"city":["miko"]},"experience":{"job-title":["praca","praca2"],"employer":["kierwonik","kierownik2"],"start-date":["2019-12-11","2019-12-01"],"end-date":["2019-12-13","2019-12-09"],"city":["kato","szczecin"],"description":["balakdjaojdexpirience","egegegegeeg"]},"education":{"school-name":["wypizdawka","borobor"],"specialization":["jebanko","xd"],"start-date":["2019-12-10","2019-12-03"],"end-date":["2019-12-31","2019-12-26"],"city":["kato","szczecin"],"description":["ja jebie co za smiech","oby dzialalo"]},"skills":{"languages":{"lang":["eng","czeski"],"level":["2","1"]},"skills":{"skill":["bdbd","wazenie","krojenie"],"level":["2","3","2"]}},"additional":{"cv":["ciwi"],"cover-letter":["liscikmot"],"certificates":["certyfikacik"],"courses":["treninge"]},"counters":{"personal-data":1,"experience":2,"education":2,"language":2,"skill":3,"cv":1,"cover-letter":1,"certificate":1,"course":1}}