{"val":{"username":"erika","email":"eri@mi.do","password":"$2y$10$eqyiRMXu6td0lLqb8e2SkO.smcFop3kmsSjw5clEMKrhEesRAHeN2","position":"Java intern"},"pd":{"first_name":"Erika","last_name":"Er","phone":"123123123","residence_country":"Western Sahara","residence_city":"Palm"},"sk_lang":{"language":["german"],"language_level":["2"],"skill":["counting"],"skill_level":["4"]},"edu":{"school":["school of sand"],"specialization":["sand distinguishing"],"start_date":["02-02-2020"],"end_date":["04-02-2020"],"city":["sah"],"description":["procesing"]}}